llama_index/readers/imdb_review/__init__.py
llama_index/readers/imdb_review/base.py
llama_index/readers/imdb_review/scraper.py
llama_index_readers_imdb_review-0.4.2.dist-info/METADATA
llama_index_readers_imdb_review-0.4.2.dist-info/WHEEL
llama_index_readers_imdb_review-0.4.2.dist-info/licenses/LICENSE
llama_index_readers_imdb_review-0.4.2.dist-info/RECORD
