Metadata-Version: 2.4
Name: llama-index-readers-imdb-review
Version: 0.4.2
Summary: llama-index readers imdb_review integration
Author-email: Your Name <you@example.com>
Maintainer: Athe-kunal
License-Expression: GPL-2.0-only
License-File: LICENSE
Keywords: IMDB,movies,reviews
Requires-Python: <4.0,>=3.9
Requires-Dist: imdbpy==2022.7.9
Requires-Dist: llama-index-core<0.15,>=0.13.0
Requires-Dist: pandas
Requires-Dist: selenium<5,>=4.15.1
Requires-Dist: webdriver-manager==4.0.1
